README.md
setup.py
test/test-calls.py
unitig_caller/__init__.py
unitig_caller/__main__.py
unitig_caller/bifrost.py
unitig_caller.egg-info/PKG-INFO
unitig_caller.egg-info/SOURCES.txt
unitig_caller.egg-info/dependency_links.txt
unitig_caller.egg-info/entry_points.txt
unitig_caller.egg-info/not-zip-safe
unitig_caller.egg-info/top_level.txt