Metadata-Version: 2.1
Name: unitig-caller
Version: 1.2.0
Summary: unitig-caller: wrapper around mantis to detect presence of sequence elements
Home-page: https://github.com/johnlees/unitig-caller
Author: John Lees
Author-email: john@johnlees.me
License: Apache Software License
Keywords: gwas bacteria k-mer unitig
Platform: UNKNOWN
Classifier: Development Status :: 4 - Beta
Classifier: Intended Audience :: Science/Research
Classifier: Topic :: Scientific/Engineering :: Bio-Informatics
Classifier: License :: OSI Approved :: Apache Software License
Classifier: Programming Language :: Python :: 3.6
Classifier: Programming Language :: Python :: 3.7
